graphql_mcp/__init__.py
graphql_mcp/inspector.py
graphql_mcp/remote.py
graphql_mcp/server.py
graphql_mcp/templates/mcp_plugin.js
graphql_mcp-1.7.1.dist-info/licenses/LICENSE
graphql_mcp-1.7.1.dist-info/METADATA
graphql_mcp-1.7.1.dist-info/WHEEL
graphql_mcp-1.7.1.dist-info/top_level.txt
graphql_mcp-1.7.1.dist-info/RECORD
