Metadata-Version: 2.4
Name: graphql-mcp
Version: 1.7.1
Summary: A framework for building Python GraphQL MCP servers.
Author-email: Robert Parker <rob@parob.com>
License: MIT
Project-URL: Homepage, https://gitlab.com/parob/graphql-mcp
Project-URL: Repository, https://gitlab.com/parob/graphql-mcp
Keywords: GraphQL,GraphQL-API,GraphQLAPI,Server,MCP,Multi-Model-Protocol
Classifier: Development Status :: 3 - Alpha
Classifier: Intended Audience :: Developers
Classifier: Programming Language :: Python :: 3
Classifier: License :: OSI Approved :: MIT License
Classifier: Operating System :: OS Independent
Requires-Python: <3.13,>=3.11
License-File: LICENSE
Requires-Dist: graphql-core
Requires-Dist: fastmcp
Requires-Dist: graphql-api
Requires-Dist: graphql-http>=2.1.5
Requires-Dist: aiohttp
Dynamic: license-file
